.gitignore
.pylintrc
.readthedocs.yml
.travis.yml
CODE_OF_CONDUCT.md
LICENSE
README.rst
adafruit_mlx90393.py
requirements.txt
setup.py
adafruit_circuitpython_mlx90939.egg-info/PKG-INFO
adafruit_circuitpython_mlx90939.egg-info/SOURCES.txt
adafruit_circuitpython_mlx90939.egg-info/dependency_links.txt
adafruit_circuitpython_mlx90939.egg-info/requires.txt
adafruit_circuitpython_mlx90939.egg-info/top_level.txt
docs/api.rst
docs/conf.py
docs/examples.rst
docs/index.rst
docs/_static/favicon.ico
examples/adafruit_mlx90393_simpletest.py