Metadata-Version: 2.1
Name: adafruit-circuitpython-mlx90939
Version: 1.1.1
Summary: CircuitPython driver for the MLX90393 3-axis magnetometer.
Home-page: https://github.com/adafruit/Adafruit_CircuitPython_MLX90393
Author: Adafruit Industries
Author-email: circuitpython@adafruit.com
License: MIT
Keywords: adafruit three-axis magnetometer magnet mlx90393 hardware micropython circuitpython
Platform: UNKNOWN
Classifier: Development Status :: 3 - Alpha
Classifier: Intended Audience :: Developers
Classifier: Topic :: Software Development :: Libraries
Classifier: Topic :: System :: Hardware
Classifier: License :: OSI Approved :: MIT License
Classifier: Programming Language :: Python :: 3
Classifier: Programming Language :: Python :: 3.4
Classifier: Programming Language :: Python :: 3.5
